check_ldap_ppolicy_lockout/__init__.py
check_ldap_ppolicy_lockout/args.py
check_ldap_ppolicy_lockout/config.py
check_ldap_ppolicy_lockout/ldap.py
check_ldap_ppolicy_lockout/nagios.py
check_ldap_ppolicy_lockout-0.1.0.dist-info/LICENSE
check_ldap_ppolicy_lockout-0.1.0.dist-info/METADATA
check_ldap_ppolicy_lockout-0.1.0.dist-info/WHEEL
check_ldap_ppolicy_lockout-0.1.0.dist-info/entry_points.txt
check_ldap_ppolicy_lockout-0.1.0.dist-info/RECORD
