Metadata-Version: 2.3
Name: check_ldap_ppolicy_lockout
Version: 0.1.0
Summary: Nagios plugin to report LDAP users locked by the ppolicy overlay
License: GNU Public License v3
Author: Harald Wilhelmi
Author-email: harald.wilhelmi@uni-heidelberg.de
Requires-Python: >=3.13
Classifier: License :: Other/Proprietary License
Classifier: Programming Language :: Python :: 3
Classifier: Programming Language :: Python :: 3.13
Requires-Dist: ldap3 (>=2.9.1,<3.0.0)
Requires-Dist: pyyaml (>=6.0.3,<7.0.0)
Project-URL: Homepage, https://github.com/dieterich-lab/check_ldap_ppolicy_lockout
Project-URL: Issues, https://github.com/dieterich-lab/check_ldap_ppolicy_lockout/issues
